ladyrick/__init__.py
ladyrick/allgather.py
ladyrick/debug.py
ladyrick/loader.py
ladyrick/pickle.py
ladyrick/pprint.py
ladyrick/print_utils.py
ladyrick/terminal.py
ladyrick/torch.py
ladyrick/typing.py
ladyrick/utils.py
ladyrick/vars.py
ladyrick/cli/calc.py
ladyrick/cli/multi_ssh.py
ladyrick/cli/multi_ssh_remote_head.py
ladyrick/cli/psf.py
ladyrick/cli/tee.py
ladyrick/cli/test_args.py
ladyrick/cli/test_signal.py
ladyrick/patch/__init__.py
ladyrick/patch/print.py
ladyrick/patch/rich_print.py
ladyrick/patch/python/__init__.py
ladyrick/patch/python/__main__.py
ladyrick/patch/python/usercustomize.py
ladyrick-0.6.7.dist-info/licenses/LICENSE
ladyrick-0.6.7.dist-info/METADATA
ladyrick-0.6.7.dist-info/WHEEL
ladyrick-0.6.7.dist-info/entry_points.txt
ladyrick-0.6.7.dist-info/top_level.txt
ladyrick-0.6.7.dist-info/RECORD
