Metadata-Version: 2.4
Name: ladyrick
Version: 0.6.7
Summary: ladyrick's tools
Author-email: ladyrick <ladyrick@qq.com>
License-Expression: MIT
Project-URL: Homepage, https://github.com/ladyrick/ladyrick-pip
Project-URL: Documentation, https://github.com/ladyrick/ladyrick-pip
Project-URL: Repository, https://github.com/ladyrick/ladyrick-pip
Keywords: utility,tool
Classifier: Programming Language :: Python :: 3
Classifier: Programming Language :: Python :: 3.9
Classifier: Programming Language :: Python :: 3.10
Classifier: Programming Language :: Python :: 3.11
Classifier: Programming Language :: Python :: 3.12
Classifier: Programming Language :: Python :: 3.13
Requires-Python: >=3.9
License-File: LICENSE
Requires-Dist: rich
Requires-Dist: ipython
Requires-Dist: setproctitle>=1.3.5
Requires-Dist: debugpy
Dynamic: license-file
